chinaski/__init__.py
chinaski/__main__.py
chinaski/cli.py
chinaski/finder.py
chinaski/henry.py
chinaski/is_email.py
chinaski/read_lines.py
chinaski-1.0.2.dist-info/LICENSE
chinaski-1.0.2.dist-info/METADATA
chinaski-1.0.2.dist-info/WHEEL
chinaski-1.0.2.dist-info/top_level.txt
chinaski-1.0.2.dist-info/RECORD
