Metadata-Version: 2.1
Name: chinaski
Version: 1.0.2
Summary: Detect email addresses in files
Author: w0rmr1d3r
License: GPLv3
Project-URL: Homepage, https://github.com/w0rmr1d3r/chinaski
Project-URL: Repository, https://github.com/w0rmr1d3r/chinaski
Project-URL: Bug Tracker, https://github.com/w0rmr1d3r/chinaski/issues
Project-URL: Documentation, https://github.com/w0rmr1d3r/chinaski
Project-URL: Changelog, https://github.com/w0rmr1d3r/chinaski/releases
Classifier: Programming Language :: Python
Classifier: Programming Language :: Python :: 3
Classifier: Programming Language :: Python :: 3.9
Classifier: Programming Language :: Python :: 3.10
Classifier: Programming Language :: Python :: 3.11
Classifier: Programming Language :: Python :: 3.12
Requires-Python: >=3.9.0
License-File: LICENSE
Requires-Dist: click >=8.1.3
Provides-Extra: dev
Requires-Dist: autoflake >=2.0.0 ; extra == 'dev'
Requires-Dist: black >=23.0.0 ; extra == 'dev'
Requires-Dist: coverage >=7.0.0 ; extra == 'dev'
Requires-Dist: docformatter >=1.5.1 ; extra == 'dev'
Requires-Dist: flake8 >=6.0.0 ; extra == 'dev'
Requires-Dist: isort >=5.12.0 ; extra == 'dev'
Requires-Dist: pip-tools >=6.12.0 ; extra == 'dev'
Requires-Dist: pylint >=2.16.0 ; extra == 'dev'
Requires-Dist: pytest >=7.0.0 ; extra == 'dev'
